chess_classification/__init__.py
chess_classification/chess_classification.py
chess_classification/genPgn.py
chess_classification/importPgn.py
chess_classification-0.0.5.dist-info/LICENSE.txt
chess_classification-0.0.5.dist-info/METADATA
chess_classification-0.0.5.dist-info/WHEEL
chess_classification-0.0.5.dist-info/entry_points.txt
chess_classification-0.0.5.dist-info/top_level.txt
chess_classification-0.0.5.dist-info/RECORD
